Metadata-Version: 2.1
Name: MOHAMMEDCAL
Version: 0.post1
Summary: For a test
Author: MO-SALAH
License-File: LICENCE.txt
